mdx_twitchmoticons.py
setup.py
mdx_twitchmoticons.egg-info/PKG-INFO
mdx_twitchmoticons.egg-info/SOURCES.txt
mdx_twitchmoticons.egg-info/dependency_links.txt
mdx_twitchmoticons.egg-info/requires.txt
mdx_twitchmoticons.egg-info/top_level.txt