Metadata-Version: 1.1
Name: mdx-twitchmoticons
Version: 1.3
Summary: Python-Markdown extension to support Twitch.tv-style emoticons.
Home-page: https://github.com/andrewphorn/markdown.twitchmoticons
Author: Andrew Horn
Author-email: andrewphorn@gmail.com
License: UNKNOWN
Platform: UNKNOWN
Classifier: Operating System :: OS Independent
Classifier: Intended Audience :: Developers
Classifier: Environment :: Web Environment
Classifier: Programming Language :: Python
Classifier: Topic :: Text Processing :: Filters
Classifier: Topic :: Text Processing :: Markup :: HTML
